SwSpotify/__init__.py
SwSpotify/__main__.py
SwSpotify/spotify.py
SwSpotify/web_server.py
swspotify-1.2.3.dist-info/LICENSE
swspotify-1.2.3.dist-info/WHEEL
swspotify-1.2.3.dist-info/METADATA
swspotify-1.2.3.dist-info/RECORD
