Metadata-Version: 2.1
Name: swspotify
Version: 1.2.3
Summary: Get currently playing song and artist from Spotify faster without using the API.
Home-page: https://github.com/SwagLyrics/SwSpotify
License: MIT
Keywords: spotify,swaglyrics,python,app
Author: Aadi Bajpai
Author-email: clash@swaglyrics.dev
Requires-Python: >=3.6,<4.0
Classifier: License :: OSI Approved :: MIT License
Classifier: Operating System :: OS Independent
Classifier: Programming Language :: Python :: 3
Classifier: Programming Language :: Python :: 3.10
Classifier: Programming Language :: Python :: 3.6
Classifier: Programming Language :: Python :: 3.7
Classifier: Programming Language :: Python :: 3.8
Classifier: Programming Language :: Python :: 3.9
Requires-Dist: Flask-Cors (>=3.0.10,<4.0.0)
Requires-Dist: dbus-python (>=1.2.16,<2.0.0); sys_platform == "linux"
Requires-Dist: flask (>=2.0.1,<3.0.0)
Requires-Dist: pywin32 (>=301,<304); sys_platform == "win32"
Requires-Dist: requests (>=2.25.1,<3.0.0)
Project-URL: Documentation, https://github.com/SwagLyrics/SwSpotify/blob/master/README.md
Project-URL: Repository, https://github.com/SwagLyrics/SwSpotify
